blobconverter/__init__.py
blobconverter/__main__.py
blobconverter/test.py
blobconverter-1.4.2.dist-info/METADATA
blobconverter-1.4.2.dist-info/WHEEL
blobconverter-1.4.2.dist-info/entry_points.txt
blobconverter-1.4.2.dist-info/top_level.txt
blobconverter-1.4.2.dist-info/RECORD
