Metadata-Version: 2.1
Name: blobconverter
Version: 1.4.2
Summary: The tool that allows you to convert neural networks to MyriadX blob
Home-page: https://github.com/luxonis/blobconverter
Author: Luxonis
Author-email: support@luxonis.com
License: MIT
Project-URL: Bug Tracker, https://github.com/luxonis/blobconverter/issues
Project-URL: Source Code, https://github.com/luxonis/blobconverter/tree/master/cli
Keywords: blobconverter blob converter myriadx openvino tensorflow caffe ir
Platform: UNKNOWN
Classifier: License :: OSI Approved :: MIT License
Classifier: Programming Language :: Python
Classifier: Programming Language :: Python :: 3
Classifier: Programming Language :: Python :: 3.6
Classifier: Programming Language :: Python :: 3.7
Classifier: Programming Language :: Python :: 3.8
Classifier: Programming Language :: Python :: 3.9
Classifier: Programming Language :: Python :: 3.10
